pygifconvt_test_bell_stone/__init__.py
pygifconvt_test_bell_stone/converter.py
pygifconvt_test_bell_stone-1.0.1.dist-info/LICENSE
pygifconvt_test_bell_stone-1.0.1.dist-info/METADATA
pygifconvt_test_bell_stone-1.0.1.dist-info/WHEEL
pygifconvt_test_bell_stone-1.0.1.dist-info/top_level.txt
pygifconvt_test_bell_stone-1.0.1.dist-info/RECORD
